mcp_k8s_install/main.py
mcp_k8s_install/core/mcp_instance.py
mcp_k8s_install/core/ssh_client.py
mcp_k8s_install/function/install.py
mcp_k8s_install/function/utils.py
mcp_k8s_install-0.1.0.dist-info/METADATA
mcp_k8s_install-0.1.0.dist-info/WHEEL
mcp_k8s_install-0.1.0.dist-info/top_level.txt
mcp_k8s_install-0.1.0.dist-info/RECORD
