Metadata-Version: 2.4
Name: mcp_k8s_install
Version: 0.1.0
Summary: use mcp, easy install k8s
Author-email: maruduck <maruduck1117@gmail.com>
Project-URL: Homepage, https://github.com/maruduck/MCP_k8s
Keywords: mcp,k8s,kubernetes,auto installer
Requires-Python: >=3.12
Requires-Dist: mcp[cli]>=1.6.0
Requires-Dist: paramiko>=3.5.1
Requires-Dist: setuptools>=80.9.0
